aidesk/__init__.py
aidesk/cli.py
aidesk/instance_housekeeper.py
aidesk/server.py
aidesk/session.py
aidesk/utils.py
aidesk/api_handlers/__init__.py
aidesk/api_handlers/auth.py
aidesk/api_handlers/file_handling.py
aidesk/api_handlers/home.py
aidesk/api_handlers/instance_management.py
aidesk/client/__init__.py
aidesk/client/registration.py
aidesk/static/css/style.css
aidesk/static/js/login.js
aidesk/static/js/manage-instances.js
aidesk/templates/index.html
aidesk/templates/login.html
aidesk/templates/login2.html
aidesk/templates/manage-instances.html
aidesk/templates/upload_file.html
aidesk-0.3.0.dist-info/licenses/LICENSE
aidesk-0.3.0.dist-info/METADATA
aidesk-0.3.0.dist-info/WHEEL
aidesk-0.3.0.dist-info/entry_points.txt
aidesk-0.3.0.dist-info/top_level.txt
aidesk-0.3.0.dist-info/RECORD
