Metadata-Version: 2.4
Name: aidesk
Version: 0.3.0
Summary: A simple web service with file operations and instance management
Home-page: https://github.com/levindemo/aidesk
Author: levin
Author-email: your.email@example.com
Project-URL: Bug Reports, https://github.com/yourusername/aidesk/issues
Project-URL: Source, https://github.com/yourusername/aidesk/
Keywords: web service,file management,instance management
Classifier: Development Status :: 3 - Alpha
Classifier: Intended Audience :: Developers
Classifier: License :: OSI Approved :: MIT License
Classifier: Programming Language :: Python :: 3
Classifier: Programming Language :: Python :: 3.6
Classifier: Programming Language :: Python :: 3.7
Classifier: Programming Language :: Python :: 3.8
Classifier: Programming Language :: Python :: 3.9
Requires-Python: >=3.6, <4
License-File: LICENSE
Requires-Dist: requests>=2.25.1
Dynamic: author
Dynamic: author-email
Dynamic: classifier
Dynamic: description
Dynamic: description-content-type
Dynamic: home-page
Dynamic: keywords
Dynamic: license-file
Dynamic: project-url
Dynamic: requires-dist
Dynamic: requires-python
Dynamic: summary
